chalicedoc.py
chalicedoc-0.3.dist-info/DESCRIPTION.rst
chalicedoc-0.3.dist-info/METADATA
chalicedoc-0.3.dist-info/RECORD
chalicedoc-0.3.dist-info/WHEEL
chalicedoc-0.3.dist-info/metadata.json
chalicedoc-0.3.dist-info/top_level.txt
