Metadata-Version: 2.0
Name: chalicedoc
Version: 0.3
Summary: Chalice route reStructuredText autodoc directive for docutils/Sphinx.
Home-page: https://github.com/amaas-fintech/chalicedoc
Author: Joshua Ringer
Author-email: josh.ringer@argomi.com
License: Apache License Version 2.0
Keywords: chalice docutils rst sphinx
Platform: UNKNOWN
Classifier: Development Status :: 3 - Alpha
Classifier: Environment :: Plugins
Classifier: Framework :: Sphinx :: Extension
Classifier: Intended Audience :: Developers
Classifier: License :: OSI Approved :: Apache Software License
Classifier: Natural Language :: English
Classifier: Operating System :: OS Independent
Classifier: Programming Language :: Python
Classifier: Programming Language :: Python :: 2.7
Classifier: Programming Language :: Python :: 3.3
Classifier: Programming Language :: Python :: 3.4
Classifier: Programming Language :: Python :: 3.5
Classifier: Programming Language :: Python :: 3.6
Classifier: Topic :: Documentation
Classifier: Topic :: Documentation :: Sphinx
Classifier: Topic :: Software Development :: Documentation
Requires-Dist: docutils
Requires-Dist: sphinx
